.DS_Store
esiosdata/__init__.py
esiosdata/__main__.py
esiosdata/classdataesios.py
esiosdata/esios_config.py
esiosdata/facturapvpc.py
esiosdata/importdemdata.py
esiosdata/importpvpcdata.py
esiosdata/perfilesconsumopvpc.py
esiosdata/pvpcplot.py
esiosdata/prettyprinting/__init__.py
esiosdata/templates/factura_pvpc.html
esiosdata/templates/factura_pvpc_web.html
esiosdata/templates/layout.html
esiosdata-0.6.10.dist-info/DESCRIPTION.rst
esiosdata-0.6.10.dist-info/LICENSE.txt
esiosdata-0.6.10.dist-info/METADATA
esiosdata-0.6.10.dist-info/RECORD
esiosdata-0.6.10.dist-info/WHEEL
esiosdata-0.6.10.dist-info/entry_points.txt
esiosdata-0.6.10.dist-info/metadata.json
esiosdata-0.6.10.dist-info/top_level.txt
