Metadata-Version: 2.0
Name: esiosdata
Version: 0.6.10
Summary: Web Scraper para datos de demanda, producción y coste de la energía eléctrica en España, y simulador de facturación eléctrica según el PVPC..
Home-page: https://github.com/azogue/esiosdata
Author: Eugenio Panadero
Author-email: azogue.lab@gmail.com
License: MIT
Keywords: web scraper,energy,esios,ree,pvpc,electricidad
Platform: UNKNOWN
Classifier: Development Status :: 4 - Beta
Classifier: Intended Audience :: Education
Classifier: Intended Audience :: Information Technology
Classifier: Intended Audience :: Science/Research
Classifier: Topic :: Scientific/Engineering :: Information Analysis
Classifier: License :: OSI Approved :: MIT License
Classifier: Natural Language :: Spanish
Classifier: Operating System :: OS Independent
Classifier: Programming Language :: Python :: 3.5
Requires-Dist: dataweb
Requires-Dist: jinja2
Requires-Dist: matplotlib
Requires-Dist: numpy
Requires-Dist: pandas
Requires-Dist: pytz
Requires-Dist: termcolor
